__init__.py
arb_tehran_finance/__init__.py
arb_tehran_finance/codal/__init__.py
arb_tehran_finance/codal/codal_analysis.py
arb_tehran_finance/codal/codal_report.py
arb_tehran_finance/derivative/__init__.py
arb_tehran_finance/derivative/future.py
arb_tehran_finance/derivative/option.py
arb_tehran_finance/eco/__init__.py
arb_tehran_finance/eco/eco_analysis.py
arb_tehran_finance/eco/eco_report.py
arb_tehran_finance/ime/__init__.py
arb_tehran_finance/ime/ime_analysis.py
arb_tehran_finance/ime/ime_report.py
arb_tehran_finance/sundry/__init__.py
arb_tehran_finance/sundry/utility_functions.py
arb_tehran_finance/tse/__init__.py
arb_tehran_finance/tse/tse_analysis.py
arb_tehran_finance/tse/tse_report.py
arb_tehran_finance-0.0.30.dist-info/METADATA
arb_tehran_finance-0.0.30.dist-info/WHEEL
arb_tehran_finance-0.0.30.dist-info/top_level.txt
arb_tehran_finance-0.0.30.dist-info/RECORD
