Metadata-Version: 2.4
Name: arb_tehran_finance
Version: 0.0.30
Summary: A comprehensive module for Iranian financial markets, including data retrieval and analysis for macroeconomics, capital markets, commodity exchange, derivatives, gold, real estate and more.
Author-email: alireza bagheri <alirbagheri1400@gmail.com>
License: MIT
Project-URL: Homepage, https://github.com/alirzabaghrii/arb_tehran_finance
Project-URL: Issues, https://github.com/alirzabaghrii/arb_tehran_finance/issues
Classifier: Programming Language :: Python :: 3
Classifier: Operating System :: OS Independent
Requires-Python: >=3.12
Requires-Dist: aiohttp>=3.11.11
Requires-Dist: asyncio>=3.4.3
Requires-Dist: beautifulsoup4>=4.12.3
Requires-Dist: DateTime>=5.5
Requires-Dist: fake-useragent>=2.0.3
Requires-Dist: ipython>=8.12.3
Requires-Dist: jdatetime>=5.0.0
Requires-Dist: numpy>=2.2.2
Requires-Dist: pandas>=2.2.3
Requires-Dist: persiantools>=5.2.0
Requires-Dist: requests>=2.32.3
Requires-Dist: unsync>=1.4.0
Requires-Dist: urllib3>=2.2.3
Requires-Dist: selenium>=4.28.1
Requires-Dist: webdriver-manager>=4.0.2
Requires-Dist: bs4>=0.0.2
Requires-Dist: typing_extensions>=4.12.2
Requires-Dist: convertdate>=2.4.0
Requires-Dist: scipy>=1.14.1
